Metadata-Version: 2.1
Name: pqnha-cozinha
Version: 0.1.1
Summary: Início do projeto paçoquinha (aplicativo para a cozinha)
Home-page: https://pypi.org/project/pqnha_cozinha/
Author: (Linux77) Academia do software livre
Author-email: leonardo@asl-sl.com.br
License: MIT
Platform: UNKNOWN
Classifier: License :: OSI Approved :: MIT License
Requires-Python: >=3.6
